[
	{
		"id": 1,
		"first_name": "Adella",
		"last_name": "Carik",
		"email": "acarik0@dot.gov"
	},
	{
		"id": 2,
		"first_name": "Ferguson",
		"last_name": "Lebang",
		"email": "flebang1@yahoo.com"
	},
	{
		"id": 3,
		"first_name": "Bendite",
		"last_name": "Huston",
		"email": "bhuston2@google.cn"
	},
	{
		"id": 4,
		"first_name": "Ursola",
		"last_name": "Going",
		"email": "ugoing3@cocolog-nifty.com"
	},
	{
		"id": 5,
		"first_name": "Theadora",
		"last_name": "Kennifeck",
		"email": "tkennifeck4@youtu.be"
	},
	{
		"id": 6,
		"first_name": "Giselle",
		"last_name": "Piwall",
		"email": "gpiwall5@parallels.com"
	},
	{
		"id": 7,
		"first_name": "Willa",
		"last_name": "Balcers",
		"email": "wbalcers6@addtoany.com"
	},
	{
		"id": 8,
		"first_name": "Lazare",
		"last_name": "Wearn",
		"email": "lwearn7@fc2.com"
	},
	{
		"id": 9,
		"first_name": "Sauveur",
		"last_name": "Elmes",
		"email": "selmes8@ucla.edu"
	},
	{
		"id": 10,
		"first_name": "Nicky",
		"last_name": "Servant",
		"email": "nservant9@soup.io"
	},
	{
		"id": 11,
		"first_name": "Arny",
		"last_name": "Cadigan",
		"email": "acadigana@gnu.org"
	},
	{
		"id": 12,
		"first_name": "Katine",
		"last_name": "Card",
		"email": "kcardb@cnbc.com"
	},
	{
		"id": 13,
		"first_name": "Bentlee",
		"last_name": "Burfitt",
		"email": "bburfittc@cbslocal.com"
	},
	{
		"id": 14,
		"first_name": "Annetta",
		"last_name": "Wilby",
		"email": "awilbyd@comsenz.com"
	},
	{
		"id": 15,
		"first_name": "Malanie",
		"last_name": "Benadette",
		"email": "mbenadettee@jigsy.com"
	}
]
